superpaste/__init__.py
superpaste/__main__.py
superpaste/__version__.py
superpaste/backends/__init__.py
superpaste/backends/base.py
superpaste/backends/hastebin_com.py
superpaste/backends/hastebin_skyra_pw.py
superpaste/backends/hst_sh.py
superpaste/backends/mystb_in.py
superpaste/backends/paste_ee.py
superpaste-1.0.0rc2.dist-info/LICENSE
superpaste-1.0.0rc2.dist-info/METADATA
superpaste-1.0.0rc2.dist-info/WHEEL
superpaste-1.0.0rc2.dist-info/entry_points.txt
superpaste-1.0.0rc2.dist-info/top_level.txt
superpaste-1.0.0rc2.dist-info/RECORD
